{
  "metadata": {
    "generated_at": "2026-04-14T18:33:57.109337+00:00",
    "job_offers_fetched": 20,
    "sponsors_fetched": 140986,
    "matched_rows": 30
  },
  "matches": [
    {
      "offer": {
        "source": "reed",
        "external_id": 56702664,
        "title": "Software Engineer",
        "company": "Saab UK",
        "location": "Hull",
        "salary_min": null,
        "salary_max": null,
        "currency": "GBP",
        "contract_type": null,
        "contract_time": null,
        "posted_at": "26/03/2026",
        "url": "https://www.reed.co.uk/jobs/software-engineer/56702664",
        "raw": {
          "jobId": 56702664,
          "employerId": 660149,
          "employerName": "Saab UK",
          "employerProfileId": null,
          "employerProfileName": null,
          "jobTitle": "Software Engineer",
          "locationName": "Hull",
          "minimumSalary": null,
          "maximumSalary": null,
          "currency": null,
          "expirationDate": "23/04/2026",
          "date": "26/03/2026",
          "jobDescription": "Introduction Saab UK is part of Scandinavia's largest defence company, bringing together the best of Swedish and British innovation. Saab offers world-leading solutions and services in defence, aviation, space, and civil security to keep people and society safe. Our UK presence has been growing at pace, meaning we can offer a wide range of opportunities for personal fulfilment and career growth. We currently employ over 600 people across eight s... ",
          "applications": 54,
          "jobUrl": "https://www.reed.co.uk/jobs/software-engineer/56702664"
        }
      },
      "sponsor": {
        "organisation_name": "SAAB UK LIMITED",
        "town_city": "London",
        "county": "NULL",
        "type_rating": "Worker (A rating)",
        "route": "Global Business Mobility: Senior or Specialist Worker"
      }
    },
    {
      "offer": {
        "source": "reed",
        "external_id": 56702664,
        "title": "Software Engineer",
        "company": "Saab UK",
        "location": "Hull",
        "salary_min": null,
        "salary_max": null,
        "currency": "GBP",
        "contract_type": null,
        "contract_time": null,
        "posted_at": "26/03/2026",
        "url": "https://www.reed.co.uk/jobs/software-engineer/56702664",
        "raw": {
          "jobId": 56702664,
          "employerId": 660149,
          "employerName": "Saab UK",
          "employerProfileId": null,
          "employerProfileName": null,
          "jobTitle": "Software Engineer",
          "locationName": "Hull",
          "minimumSalary": null,
          "maximumSalary": null,
          "currency": null,
          "expirationDate": "23/04/2026",
          "date": "26/03/2026",
          "jobDescription": "Introduction Saab UK is part of Scandinavia's largest defence company, bringing together the best of Swedish and British innovation. Saab offers world-leading solutions and services in defence, aviation, space, and civil security to keep people and society safe. Our UK presence has been growing at pace, meaning we can offer a wide range of opportunities for personal fulfilment and career growth. We currently employ over 600 people across eight s... ",
          "applications": 54,
          "jobUrl": "https://www.reed.co.uk/jobs/software-engineer/56702664"
        }
      },
      "sponsor": {
        "organisation_name": "SAAB UK LIMITED",
        "town_city": "London",
        "county": "NULL",
        "type_rating": "Worker (A rating)",
        "route": "Skilled Worker"
      }
    },
    {
      "offer": {
        "source": "reed",
        "external_id": 55769471,
        "title": "Software Engineer",
        "company": "AJ Bell",
        "location": "Manchester",
        "salary_min": null,
        "salary_max": null,
        "currency": "GBP",
        "contract_type": null,
        "contract_time": null,
        "posted_at": "16/09/2025",
        "url": "https://www.reed.co.uk/jobs/software-engineer/55769471",
        "raw": {
          "jobId": 55769471,
          "employerId": 566198,
          "employerName": "AJ Bell",
          "employerProfileId": null,
          "employerProfileName": null,
          "jobTitle": "Software Engineer",
          "locationName": "Manchester",
          "minimumSalary": null,
          "maximumSalary": null,
          "currency": null,
          "expirationDate": "22/05/2026",
          "date": "16/09/2025",
          "jobDescription": "Job Description We now have&nbsp;an exciting opportunity for a Software Engineer to join a forward thinking company offering a collaborative team working environment, training and excellent career progression. Our strategy is to have a cross functional development team, with team members working on all areas of our technology stack and propositions. What we're looking for: We’re looking for an intelligent, energetic and driven software engineer ... ",
          "applications": 203,
          "jobUrl": "https://www.reed.co.uk/jobs/software-engineer/55769471"
        }
      },
      "sponsor": {
        "organisation_name": "AJ Bell Plc",
        "town_city": "Salford Quays",
        "county": "Manchester",
        "type_rating": "Worker (A rating)",
        "route": "Skilled Worker"
      }
    },
    {
      "offer": {
        "source": "reed",
        "external_id": 56735707,
        "title": "Firmware/Software Engineer",
        "company": "Unipart",
        "location": "Stockport",
        "salary_min": 40000.0,
        "salary_max": 40000.0,
        "currency": "GBP",
        "contract_type": null,
        "contract_time": null,
        "posted_at": "02/04/2026",
        "url": "https://www.reed.co.uk/jobs/firmware-software-engineer/56735707",
        "raw": {
          "jobId": 56735707,
          "employerId": 689211,
          "employerName": "Unipart",
          "employerProfileId": null,
          "employerProfileName": null,
          "jobTitle": "Firmware/Software Engineer",
          "locationName": "Stockport",
          "minimumSalary": 40000.0,
          "maximumSalary": 40000.0,
          "currency": "GBP",
          "expirationDate": "14/05/2026",
          "date": "02/04/2026",
          "jobDescription": "Salary: &nbsp;Circa 40,000&nbsp; Hours: &nbsp;37.5&nbsp; Contract: &nbsp;Full time&nbsp; Location: &nbsp;Stockport&nbsp; At Park Signalling we utilise our specialist engineering skills and knowledge to deliver products and services including consultancy and projects. We deliver design and development, application engineering, prototype manufacture, repair and consultancy at any stage in the life-cycle of a system or product. We design, manufactu... ",
          "applications": 13,
          "jobUrl": "https://www.reed.co.uk/jobs/firmware-software-engineer/56735707"
        }
      },
      "sponsor": {
        "organisation_name": "UNIPART GROUP LIMITED",
        "town_city": "COWLEY",
        "county": "OXFORD",
        "type_rating": "Worker (A rating)",
        "route": "Global Business Mobility: Senior or Specialist Worker"
      }
    },
    {
      "offer": {
        "source": "reed",
        "external_id": 56735707,
        "title": "Firmware/Software Engineer",
        "company": "Unipart",
        "location": "Stockport",
        "salary_min": 40000.0,
        "salary_max": 40000.0,
        "currency": "GBP",
        "contract_type": null,
        "contract_time": null,
        "posted_at": "02/04/2026",
        "url": "https://www.reed.co.uk/jobs/firmware-software-engineer/56735707",
        "raw": {
          "jobId": 56735707,
          "employerId": 689211,
          "employerName": "Unipart",
          "employerProfileId": null,
          "employerProfileName": null,
          "jobTitle": "Firmware/Software Engineer",
          "locationName": "Stockport",
          "minimumSalary": 40000.0,
          "maximumSalary": 40000.0,
          "currency": "GBP",
          "expirationDate": "14/05/2026",
          "date": "02/04/2026",
          "jobDescription": "Salary: &nbsp;Circa 40,000&nbsp; Hours: &nbsp;37.5&nbsp; Contract: &nbsp;Full time&nbsp; Location: &nbsp;Stockport&nbsp; At Park Signalling we utilise our specialist engineering skills and knowledge to deliver products and services including consultancy and projects. We deliver design and development, application engineering, prototype manufacture, repair and consultancy at any stage in the life-cycle of a system or product. We design, manufactu... ",
          "applications": 13,
          "jobUrl": "https://www.reed.co.uk/jobs/firmware-software-engineer/56735707"
        }
      },
      "sponsor": {
        "organisation_name": "UNIPART GROUP LIMITED",
        "town_city": "COWLEY",
        "county": "OXFORD",
        "type_rating": "Worker (A rating)",
        "route": "Skilled Worker"
      }
    },
    {
      "offer": {
        "source": "reed",
        "external_id": 56735707,
        "title": "Firmware/Software Engineer",
        "company": "Unipart",
        "location": "Stockport",
        "salary_min": 40000.0,
        "salary_max": 40000.0,
        "currency": "GBP",
        "contract_type": null,
        "contract_time": null,
        "posted_at": "02/04/2026",
        "url": "https://www.reed.co.uk/jobs/firmware-software-engineer/56735707",
        "raw": {
          "jobId": 56735707,
          "employerId": 689211,
          "employerName": "Unipart",
          "employerProfileId": null,
          "employerProfileName": null,
          "jobTitle": "Firmware/Software Engineer",
          "locationName": "Stockport",
          "minimumSalary": 40000.0,
          "maximumSalary": 40000.0,
          "currency": "GBP",
          "expirationDate": "14/05/2026",
          "date": "02/04/2026",
          "jobDescription": "Salary: &nbsp;Circa 40,000&nbsp; Hours: &nbsp;37.5&nbsp; Contract: &nbsp;Full time&nbsp; Location: &nbsp;Stockport&nbsp; At Park Signalling we utilise our specialist engineering skills and knowledge to deliver products and services including consultancy and projects. We deliver design and development, application engineering, prototype manufacture, repair and consultancy at any stage in the life-cycle of a system or product. We design, manufactu... ",
          "applications": 13,
          "jobUrl": "https://www.reed.co.uk/jobs/firmware-software-engineer/56735707"
        }
      },
      "sponsor": {
        "organisation_name": "Lucchini Unipart Rail Limited",
        "town_city": "Manchester",
        "county": "",
        "type_rating": "Worker (A rating)",
        "route": "Skilled Worker"
      }
    },
    {
      "offer": {
        "source": "reed",
        "external_id": 56632950,
        "title": "Software Developer Apprentice",
        "company": "QA",
        "location": "NE14AD",
        "salary_min": 20000.0,
        "salary_max": 22000.0,
        "currency": "GBP",
        "contract_type": null,
        "contract_time": null,
        "posted_at": "12/03/2026",
        "url": "https://www.reed.co.uk/jobs/software-developer-apprentice/56632950",
        "raw": {
          "jobId": 56632950,
          "employerId": 500373,
          "employerName": "QA",
          "employerProfileId": null,
          "employerProfileName": null,
          "jobTitle": "Software Developer Apprentice",
          "locationName": "NE14AD",
          "minimumSalary": 20000.0,
          "maximumSalary": 22000.0,
          "currency": "GBP",
          "expirationDate": "23/04/2026",
          "date": "12/03/2026",
          "jobDescription": "Apprentices are in demand! Why choose our Software Engineer Level 4 apprenticeship? Our Software Engineer Level 4 Apprenticeship gives learners advance skills and technical grounding to design, test and maintain software and web systems. Learners will also gain an understanding on advanced programming, systems and software development projects. Software Development is at the heart of digital transformation. With demand for services to be consume... ",
          "applications": 52,
          "jobUrl": "https://www.reed.co.uk/jobs/software-developer-apprentice/56632950"
        }
      },
      "sponsor": {
        "organisation_name": "QA Limited",
        "town_city": "London",
        "county": "NULL",
        "type_rating": "Worker (A rating)",
        "route": "Global Business Mobility: Senior or Specialist Worker"
      }
    },
    {
      "offer": {
        "source": "reed",
        "external_id": 56632950,
        "title": "Software Developer Apprentice",
        "company": "QA",
        "location": "NE14AD",
        "salary_min": 20000.0,
        "salary_max": 22000.0,
        "currency": "GBP",
        "contract_type": null,
        "contract_time": null,
        "posted_at": "12/03/2026",
        "url": "https://www.reed.co.uk/jobs/software-developer-apprentice/56632950",
        "raw": {
          "jobId": 56632950,
          "employerId": 500373,
          "employerName": "QA",
          "employerProfileId": null,
          "employerProfileName": null,
          "jobTitle": "Software Developer Apprentice",
          "locationName": "NE14AD",
          "minimumSalary": 20000.0,
          "maximumSalary": 22000.0,
          "currency": "GBP",
          "expirationDate": "23/04/2026",
          "date": "12/03/2026",
          "jobDescription": "Apprentices are in demand! Why choose our Software Engineer Level 4 apprenticeship? Our Software Engineer Level 4 Apprenticeship gives learners advance skills and technical grounding to design, test and maintain software and web systems. Learners will also gain an understanding on advanced programming, systems and software development projects. Software Development is at the heart of digital transformation. With demand for services to be consume... ",
          "applications": 52,
          "jobUrl": "https://www.reed.co.uk/jobs/software-developer-apprentice/56632950"
        }
      },
      "sponsor": {
        "organisation_name": "QA Limited",
        "town_city": "London",
        "county": "NULL",
        "type_rating": "Worker (A rating)",
        "route": "Skilled Worker"
      }
    },
    {
      "offer": {
        "source": "reed",
        "external_id": 56632950,
        "title": "Software Developer Apprentice",
        "company": "QA",
        "location": "NE14AD",
        "salary_min": 20000.0,
        "salary_max": 22000.0,
        "currency": "GBP",
        "contract_type": null,
        "contract_time": null,
        "posted_at": "12/03/2026",
        "url": "https://www.reed.co.uk/jobs/software-developer-apprentice/56632950",
        "raw": {
          "jobId": 56632950,
          "employerId": 500373,
          "employerName": "QA",
          "employerProfileId": null,
          "employerProfileName": null,
          "jobTitle": "Software Developer Apprentice",
          "locationName": "NE14AD",
          "minimumSalary": 20000.0,
          "maximumSalary": 22000.0,
          "currency": "GBP",
          "expirationDate": "23/04/2026",
          "date": "12/03/2026",
          "jobDescription": "Apprentices are in demand! Why choose our Software Engineer Level 4 apprenticeship? Our Software Engineer Level 4 Apprenticeship gives learners advance skills and technical grounding to design, test and maintain software and web systems. Learners will also gain an understanding on advanced programming, systems and software development projects. Software Development is at the heart of digital transformation. With demand for services to be consume... ",
          "applications": 52,
          "jobUrl": "https://www.reed.co.uk/jobs/software-developer-apprentice/56632950"
        }
      },
      "sponsor": {
        "organisation_name": "QA-UK LIMITED",
        "town_city": "Middlesex",
        "county": "",
        "type_rating": "Worker (A rating)",
        "route": "Skilled Worker"
      }
    },
    {
      "offer": {
        "source": "reed",
        "external_id": 56729951,
        "title": "Lead Software Engineer",
        "company": "Saab UK",
        "location": "Fareham",
        "salary_min": null,
        "salary_max": null,
        "currency": "GBP",
        "contract_type": null,
        "contract_time": null,
        "posted_at": "01/04/2026",
        "url": "https://www.reed.co.uk/jobs/lead-software-engineer/56729951",
        "raw": {
          "jobId": 56729951,
          "employerId": 660149,
          "employerName": "Saab UK",
          "employerProfileId": null,
          "employerProfileName": null,
          "jobTitle": "Lead Software Engineer",
          "locationName": "Fareham",
          "minimumSalary": null,
          "maximumSalary": null,
          "currency": null,
          "expirationDate": "29/04/2026",
          "date": "01/04/2026",
          "jobDescription": "Introduction Saab UK is part of Scandinavia's largest defence company, bringing together the best of Swedish and British innovation. Saab offers world-leading solutions and services in defence, aviation, space, and civil security to keep people and society safe. Our UK presence has been growing at pace, meaning we can offer a wide range of opportunities for personal fulfilment and career growth. We currently employ over 600 people across eight s... ",
          "applications": 9,
          "jobUrl": "https://www.reed.co.uk/jobs/lead-software-engineer/56729951"
        }
      },
      "sponsor": {
        "organisation_name": "SAAB UK LIMITED",
        "town_city": "London",
        "county": "NULL",
        "type_rating": "Worker (A rating)",
        "route": "Global Business Mobility: Senior or Specialist Worker"
      }
    },
    {
      "offer": {
        "source": "reed",
        "external_id": 56729951,
        "title": "Lead Software Engineer",
        "company": "Saab UK",
        "location": "Fareham",
        "salary_min": null,
        "salary_max": null,
        "currency": "GBP",
        "contract_type": null,
        "contract_time": null,
        "posted_at": "01/04/2026",
        "url": "https://www.reed.co.uk/jobs/lead-software-engineer/56729951",
        "raw": {
          "jobId": 56729951,
          "employerId": 660149,
          "employerName": "Saab UK",
          "employerProfileId": null,
          "employerProfileName": null,
          "jobTitle": "Lead Software Engineer",
          "locationName": "Fareham",
          "minimumSalary": null,
          "maximumSalary": null,
          "currency": null,
          "expirationDate": "29/04/2026",
          "date": "01/04/2026",
          "jobDescription": "Introduction Saab UK is part of Scandinavia's largest defence company, bringing together the best of Swedish and British innovation. Saab offers world-leading solutions and services in defence, aviation, space, and civil security to keep people and society safe. Our UK presence has been growing at pace, meaning we can offer a wide range of opportunities for personal fulfilment and career growth. We currently employ over 600 people across eight s... ",
          "applications": 9,
          "jobUrl": "https://www.reed.co.uk/jobs/lead-software-engineer/56729951"
        }
      },
      "sponsor": {
        "organisation_name": "SAAB UK LIMITED",
        "town_city": "London",
        "county": "NULL",
        "type_rating": "Worker (A rating)",
        "route": "Skilled Worker"
      }
    },
    {
      "offer": {
        "source": "reed",
        "external_id": 56729579,
        "title": "Software Engineer (GenAI)",
        "company": "AJ Bell",
        "location": "M53EE",
        "salary_min": null,
        "salary_max": null,
        "currency": "GBP",
        "contract_type": null,
        "contract_time": null,
        "posted_at": "01/04/2026",
        "url": "https://www.reed.co.uk/jobs/software-engineer-genai/56729579",
        "raw": {
          "jobId": 56729579,
          "employerId": 566198,
          "employerName": "AJ Bell",
          "employerProfileId": null,
          "employerProfileName": null,
          "jobTitle": "Software Engineer (GenAI)",
          "locationName": "M53EE",
          "minimumSalary": null,
          "maximumSalary": null,
          "currency": null,
          "expirationDate": "13/05/2026",
          "date": "01/04/2026",
          "jobDescription": "Job Description This is an fantastic opportunity for a Software Developer (GenAI) to join at an exciting time for AJ Bell as we expand the usage of AI within the business. Our GenAI development team are at the heart of this growth and ee have a strong team working environment, training and excellent career progression for the right person. Our strategy is to have a cross-functional development team, with team members working on all areas of our ... ",
          "applications": 33,
          "jobUrl": "https://www.reed.co.uk/jobs/software-engineer-genai/56729579"
        }
      },
      "sponsor": {
        "organisation_name": "AJ Bell Plc",
        "town_city": "Salford Quays",
        "county": "Manchester",
        "type_rating": "Worker (A rating)",
        "route": "Skilled Worker"
      }
    },
    {
      "offer": {
        "source": "reed",
        "external_id": 56781721,
        "title": "Software Developer Apprentice",
        "company": "QA",
        "location": "CM778YG",
        "salary_min": 22000.0,
        "salary_max": 22000.0,
        "currency": "GBP",
        "contract_type": null,
        "contract_time": null,
        "posted_at": "14/04/2026",
        "url": "https://www.reed.co.uk/jobs/software-developer-apprentice/56781721",
        "raw": {
          "jobId": 56781721,
          "employerId": 500373,
          "employerName": "QA",
          "employerProfileId": null,
          "employerProfileName": null,
          "jobTitle": "Software Developer Apprentice",
          "locationName": "CM778YG",
          "minimumSalary": 22000.0,
          "maximumSalary": 22000.0,
          "currency": "GBP",
          "expirationDate": "26/05/2026",
          "date": "14/04/2026",
          "jobDescription": "About Its Lolly: Based in Braintree, Lolly is a leading software and technology firm in the hospitality sector producing a wide range of state-of-the-art technology solutions including robot waiters, facial verification, mobile apps, EPoS and payment solutions. Our mission is to make technology simple, by implementing the best solution, incorporating the most reliable intuitive technology and to follow this with first class after-sales customer ... ",
          "applications": 0,
          "jobUrl": "https://www.reed.co.uk/jobs/software-developer-apprentice/56781721"
        }
      },
      "sponsor": {
        "organisation_name": "QA Limited",
        "town_city": "London",
        "county": "NULL",
        "type_rating": "Worker (A rating)",
        "route": "Global Business Mobility: Senior or Specialist Worker"
      }
    },
    {
      "offer": {
        "source": "reed",
        "external_id": 56781721,
        "title": "Software Developer Apprentice",
        "company": "QA",
        "location": "CM778YG",
        "salary_min": 22000.0,
        "salary_max": 22000.0,
        "currency": "GBP",
        "contract_type": null,
        "contract_time": null,
        "posted_at": "14/04/2026",
        "url": "https://www.reed.co.uk/jobs/software-developer-apprentice/56781721",
        "raw": {
          "jobId": 56781721,
          "employerId": 500373,
          "employerName": "QA",
          "employerProfileId": null,
          "employerProfileName": null,
          "jobTitle": "Software Developer Apprentice",
          "locationName": "CM778YG",
          "minimumSalary": 22000.0,
          "maximumSalary": 22000.0,
          "currency": "GBP",
          "expirationDate": "26/05/2026",
          "date": "14/04/2026",
          "jobDescription": "About Its Lolly: Based in Braintree, Lolly is a leading software and technology firm in the hospitality sector producing a wide range of state-of-the-art technology solutions including robot waiters, facial verification, mobile apps, EPoS and payment solutions. Our mission is to make technology simple, by implementing the best solution, incorporating the most reliable intuitive technology and to follow this with first class after-sales customer ... ",
          "applications": 0,
          "jobUrl": "https://www.reed.co.uk/jobs/software-developer-apprentice/56781721"
        }
      },
      "sponsor": {
        "organisation_name": "QA Limited",
        "town_city": "London",
        "county": "NULL",
        "type_rating": "Worker (A rating)",
        "route": "Skilled Worker"
      }
    },
    {
      "offer": {
        "source": "reed",
        "external_id": 56781721,
        "title": "Software Developer Apprentice",
        "company": "QA",
        "location": "CM778YG",
        "salary_min": 22000.0,
        "salary_max": 22000.0,
        "currency": "GBP",
        "contract_type": null,
        "contract_time": null,
        "posted_at": "14/04/2026",
        "url": "https://www.reed.co.uk/jobs/software-developer-apprentice/56781721",
        "raw": {
          "jobId": 56781721,
          "employerId": 500373,
          "employerName": "QA",
          "employerProfileId": null,
          "employerProfileName": null,
          "jobTitle": "Software Developer Apprentice",
          "locationName": "CM778YG",
          "minimumSalary": 22000.0,
          "maximumSalary": 22000.0,
          "currency": "GBP",
          "expirationDate": "26/05/2026",
          "date": "14/04/2026",
          "jobDescription": "About Its Lolly: Based in Braintree, Lolly is a leading software and technology firm in the hospitality sector producing a wide range of state-of-the-art technology solutions including robot waiters, facial verification, mobile apps, EPoS and payment solutions. Our mission is to make technology simple, by implementing the best solution, incorporating the most reliable intuitive technology and to follow this with first class after-sales customer ... ",
          "applications": 0,
          "jobUrl": "https://www.reed.co.uk/jobs/software-developer-apprentice/56781721"
        }
      },
      "sponsor": {
        "organisation_name": "QA-UK LIMITED",
        "town_city": "Middlesex",
        "county": "",
        "type_rating": "Worker (A rating)",
        "route": "Skilled Worker"
      }
    },
    {
      "offer": {
        "source": "reed",
        "external_id": 55925258,
        "title": "Java Software Engineer",
        "company": "Accenture",
        "location": "London",
        "salary_min": null,
        "salary_max": null,
        "currency": "GBP",
        "contract_type": null,
        "contract_time": null,
        "posted_at": "14/10/2025",
        "url": "https://www.reed.co.uk/jobs/java-software-engineer/55925258",
        "raw": {
          "jobId": 55925258,
          "employerId": 423247,
          "employerName": "Accenture",
          "employerProfileId": null,
          "employerProfileName": null,
          "jobTitle": "Java Software Engineer",
          "locationName": "London",
          "minimumSalary": null,
          "maximumSalary": null,
          "currency": null,
          "expirationDate": "26/05/2026",
          "date": "14/10/2025",
          "jobDescription": "Role: Software Engineer (Java)&nbsp; Location: London Salary: Competitive salary and package (Depending on level of experience) Any offer of employment is subject to satisfactory BPSS and the candidate being granted a level of security clearance which typically&nbsp;requires 10&nbsp;years continuous UK address history, usually including no periods of 30 consecutive days or more spent outside of the UK, and a declaration of being a British passpo... ",
          "applications": 274,
          "jobUrl": "https://www.reed.co.uk/jobs/java-software-engineer/55925258"
        }
      },
      "sponsor": {
        "organisation_name": "Accenture (UK) Limited",
        "town_city": "London",
        "county": "NULL",
        "type_rating": "Worker (A rating)",
        "route": "Skilled Worker"
      }
    },
    {
      "offer": {
        "source": "reed",
        "external_id": 55925258,
        "title": "Java Software Engineer",
        "company": "Accenture",
        "location": "London",
        "salary_min": null,
        "salary_max": null,
        "currency": "GBP",
        "contract_type": null,
        "contract_time": null,
        "posted_at": "14/10/2025",
        "url": "https://www.reed.co.uk/jobs/java-software-engineer/55925258",
        "raw": {
          "jobId": 55925258,
          "employerId": 423247,
          "employerName": "Accenture",
          "employerProfileId": null,
          "employerProfileName": null,
          "jobTitle": "Java Software Engineer",
          "locationName": "London",
          "minimumSalary": null,
          "maximumSalary": null,
          "currency": null,
          "expirationDate": "26/05/2026",
          "date": "14/10/2025",
          "jobDescription": "Role: Software Engineer (Java)&nbsp; Location: London Salary: Competitive salary and package (Depending on level of experience) Any offer of employment is subject to satisfactory BPSS and the candidate being granted a level of security clearance which typically&nbsp;requires 10&nbsp;years continuous UK address history, usually including no periods of 30 consecutive days or more spent outside of the UK, and a declaration of being a British passpo... ",
          "applications": 274,
          "jobUrl": "https://www.reed.co.uk/jobs/java-software-engineer/55925258"
        }
      },
      "sponsor": {
        "organisation_name": "Accenture (UK) Limited",
        "town_city": "London",
        "county": "NULL",
        "type_rating": "Worker (A rating)",
        "route": "Global Business Mobility: Senior or Specialist Worker"
      }
    },
    {
      "offer": {
        "source": "reed",
        "external_id": 55921921,
        "title": "Software Engineer - Leeds",
        "company": "Accenture",
        "location": "Leeds",
        "salary_min": null,
        "salary_max": null,
        "currency": "GBP",
        "contract_type": null,
        "contract_time": null,
        "posted_at": "14/10/2025",
        "url": "https://www.reed.co.uk/jobs/software-engineer-leeds/55921921",
        "raw": {
          "jobId": 55921921,
          "employerId": 423247,
          "employerName": "Accenture",
          "employerProfileId": null,
          "employerProfileName": null,
          "jobTitle": "Software Engineer - Leeds",
          "locationName": "Leeds",
          "minimumSalary": null,
          "maximumSalary": null,
          "currency": null,
          "expirationDate": "26/05/2026",
          "date": "14/10/2025",
          "jobDescription": "Software Engineer Locations: Leeds Salary: Competitive salary and package (Depending on level of experience) Please Note: Any offer of employment is subject to satisfactory SC security clearance which requires 5 years continuous UK address history, typically including no periods of 30 consecutive days or more spent outside of the UK. Note: The above information relates to a specific client requirement Accenture is a leading global professional s... ",
          "applications": 116,
          "jobUrl": "https://www.reed.co.uk/jobs/software-engineer-leeds/55921921"
        }
      },
      "sponsor": {
        "organisation_name": "Accenture (UK) Limited",
        "town_city": "London",
        "county": "NULL",
        "type_rating": "Worker (A rating)",
        "route": "Skilled Worker"
      }
    },
    {
      "offer": {
        "source": "reed",
        "external_id": 55921921,
        "title": "Software Engineer - Leeds",
        "company": "Accenture",
        "location": "Leeds",
        "salary_min": null,
        "salary_max": null,
        "currency": "GBP",
        "contract_type": null,
        "contract_time": null,
        "posted_at": "14/10/2025",
        "url": "https://www.reed.co.uk/jobs/software-engineer-leeds/55921921",
        "raw": {
          "jobId": 55921921,
          "employerId": 423247,
          "employerName": "Accenture",
          "employerProfileId": null,
          "employerProfileName": null,
          "jobTitle": "Software Engineer - Leeds",
          "locationName": "Leeds",
          "minimumSalary": null,
          "maximumSalary": null,
          "currency": null,
          "expirationDate": "26/05/2026",
          "date": "14/10/2025",
          "jobDescription": "Software Engineer Locations: Leeds Salary: Competitive salary and package (Depending on level of experience) Please Note: Any offer of employment is subject to satisfactory SC security clearance which requires 5 years continuous UK address history, typically including no periods of 30 consecutive days or more spent outside of the UK. Note: The above information relates to a specific client requirement Accenture is a leading global professional s... ",
          "applications": 116,
          "jobUrl": "https://www.reed.co.uk/jobs/software-engineer-leeds/55921921"
        }
      },
      "sponsor": {
        "organisation_name": "Accenture (UK) Limited",
        "town_city": "London",
        "county": "NULL",
        "type_rating": "Worker (A rating)",
        "route": "Global Business Mobility: Senior or Specialist Worker"
      }
    },
    {
      "offer": {
        "source": "reed",
        "external_id": 55768379,
        "title": "Senior Software Engineer",
        "company": "AJ Bell",
        "location": "Manchester",
        "salary_min": null,
        "salary_max": null,
        "currency": "GBP",
        "contract_type": null,
        "contract_time": null,
        "posted_at": "16/09/2025",
        "url": "https://www.reed.co.uk/jobs/senior-software-engineer/55768379",
        "raw": {
          "jobId": 55768379,
          "employerId": 566198,
          "employerName": "AJ Bell",
          "employerProfileId": null,
          "employerProfileName": null,
          "jobTitle": "Senior Software Engineer",
          "locationName": "Manchester",
          "minimumSalary": null,
          "maximumSalary": null,
          "currency": null,
          "expirationDate": "16/09/2026",
          "date": "16/09/2025",
          "jobDescription": "Job Description We now have&nbsp;an exciting opportunity for a Senior Software Engineer to join the Operational and Regulatory Technology department for an award-winning investment platform, offering a collaborative team working environment, training and excellent career progression. Our strategy is to have a cross functional development team, with team members working on all areas of our technology stack and propositions. What to expect: Agile ... ",
          "applications": 102,
          "jobUrl": "https://www.reed.co.uk/jobs/senior-software-engineer/55768379"
        }
      },
      "sponsor": {
        "organisation_name": "AJ Bell Plc",
        "town_city": "Salford Quays",
        "county": "Manchester",
        "type_rating": "Worker (A rating)",
        "route": "Skilled Worker"
      }
    },
    {
      "offer": {
        "source": "reed",
        "external_id": 56783900,
        "title": "Senior Software Engineer",
        "company": "FDM Group",
        "location": "London",
        "salary_min": null,
        "salary_max": null,
        "currency": "GBP",
        "contract_type": null,
        "contract_time": null,
        "posted_at": "14/04/2026",
        "url": "https://www.reed.co.uk/jobs/senior-software-engineer/56783900",
        "raw": {
          "jobId": 56783900,
          "employerId": 377422,
          "employerName": "FDM Group",
          "employerProfileId": null,
          "employerProfileName": null,
          "jobTitle": "Senior Software Engineer",
          "locationName": "London",
          "minimumSalary": null,
          "maximumSalary": null,
          "currency": null,
          "expirationDate": "26/05/2026",
          "date": "14/04/2026",
          "jobDescription": "About The Role FDM is a global business and technology consultancy seeking a Senior Software Engineer to work for our client within the defence and national security technology sector. This is initially a 12-month contract with very good prospects to extend and will be a hybrid role based in London with a requirement to attend the office at least one day per week and with up to two days’ notice when required. Our client is a UK based technology ... ",
          "applications": 8,
          "jobUrl": "https://www.reed.co.uk/jobs/senior-software-engineer/56783900"
        }
      },
      "sponsor": {
        "organisation_name": "FDM Group Limited",
        "town_city": "Brighton",
        "county": "East Sussex",
        "type_rating": "Worker (A rating)",
        "route": "Skilled Worker"
      }
    },
    {
      "offer": {
        "source": "reed",
        "external_id": 56702631,
        "title": "Lead Software Engineer",
        "company": "Sopra Steria",
        "location": "Gloucester",
        "salary_min": 55000.0,
        "salary_max": 65000.0,
        "currency": "GBP",
        "contract_type": null,
        "contract_time": null,
        "posted_at": "26/03/2026",
        "url": "https://www.reed.co.uk/jobs/lead-software-engineer/56702631",
        "raw": {
          "jobId": 56702631,
          "employerId": 616491,
          "employerName": "Sopra Steria",
          "employerProfileId": null,
          "employerProfileName": null,
          "jobTitle": "Lead Software Engineer",
          "locationName": "Gloucester",
          "minimumSalary": 55000.0,
          "maximumSalary": 65000.0,
          "currency": "GBP",
          "expirationDate": "07/05/2026",
          "date": "26/03/2026",
          "jobDescription": "Endpoint Engineer – ready for your next challenge? Do you enjoy solving complex technical problems, engineering secure and modern endpoint solutions, and working with a team who share your passion for doing things the right way? If you’re excited by the idea of shaping best-in-class endpoint platforms in a highly secure Defence environment, then this could be the perfect opportunity for you. Our Endpoint Engineering team is growing within our Ae... ",
          "applications": 35,
          "jobUrl": "https://www.reed.co.uk/jobs/lead-software-engineer/56702631"
        }
      },
      "sponsor": {
        "organisation_name": "Sopra Steria Limited",
        "town_city": "Newcastle Upon Tyne",
        "county": "NULL",
        "type_rating": "Worker (A rating)",
        "route": "Skilled Worker"
      }
    },
    {
      "offer": {
        "source": "reed",
        "external_id": 56702631,
        "title": "Lead Software Engineer",
        "company": "Sopra Steria",
        "location": "Gloucester",
        "salary_min": 55000.0,
        "salary_max": 65000.0,
        "currency": "GBP",
        "contract_type": null,
        "contract_time": null,
        "posted_at": "26/03/2026",
        "url": "https://www.reed.co.uk/jobs/lead-software-engineer/56702631",
        "raw": {
          "jobId": 56702631,
          "employerId": 616491,
          "employerName": "Sopra Steria",
          "employerProfileId": null,
          "employerProfileName": null,
          "jobTitle": "Lead Software Engineer",
          "locationName": "Gloucester",
          "minimumSalary": 55000.0,
          "maximumSalary": 65000.0,
          "currency": "GBP",
          "expirationDate": "07/05/2026",
          "date": "26/03/2026",
          "jobDescription": "Endpoint Engineer – ready for your next challenge? Do you enjoy solving complex technical problems, engineering secure and modern endpoint solutions, and working with a team who share your passion for doing things the right way? If you’re excited by the idea of shaping best-in-class endpoint platforms in a highly secure Defence environment, then this could be the perfect opportunity for you. Our Endpoint Engineering team is growing within our Ae... ",
          "applications": 35,
          "jobUrl": "https://www.reed.co.uk/jobs/lead-software-engineer/56702631"
        }
      },
      "sponsor": {
        "organisation_name": "Sopra Steria Limited",
        "town_city": "Newcastle Upon Tyne",
        "county": "NULL",
        "type_rating": "Worker (A rating)",
        "route": "Global Business Mobility: Senior or Specialist Worker"
      }
    },
    {
      "offer": {
        "source": "reed",
        "external_id": 56427863,
        "title": "Java Software Engineer",
        "company": "Accenture",
        "location": "London",
        "salary_min": null,
        "salary_max": null,
        "currency": "GBP",
        "contract_type": null,
        "contract_time": null,
        "posted_at": "04/02/2026",
        "url": "https://www.reed.co.uk/jobs/java-software-engineer/56427863",
        "raw": {
          "jobId": 56427863,
          "employerId": 423247,
          "employerName": "Accenture",
          "employerProfileId": null,
          "employerProfileName": null,
          "jobTitle": "Java Software Engineer",
          "locationName": "London",
          "minimumSalary": null,
          "maximumSalary": null,
          "currency": null,
          "expirationDate": "26/05/2026",
          "date": "04/02/2026",
          "jobDescription": "Role: Software Engineer (Java)&nbsp; Level: Associate Manager and Specialist Location: London, Bristol, Manchester and Birmingham Salary: Competitive salary and package (Depending on level of experience) Please Note: Any offer of employment is subject to satisfactory BPSS and SC security clearance which requires 5 years continuous UK address history (typically including no periods of 30 consecutive days or more spent outside of the UK) and decla... ",
          "applications": 106,
          "jobUrl": "https://www.reed.co.uk/jobs/java-software-engineer/56427863"
        }
      },
      "sponsor": {
        "organisation_name": "Accenture (UK) Limited",
        "town_city": "London",
        "county": "NULL",
        "type_rating": "Worker (A rating)",
        "route": "Skilled Worker"
      }
    },
    {
      "offer": {
        "source": "reed",
        "external_id": 56427863,
        "title": "Java Software Engineer",
        "company": "Accenture",
        "location": "London",
        "salary_min": null,
        "salary_max": null,
        "currency": "GBP",
        "contract_type": null,
        "contract_time": null,
        "posted_at": "04/02/2026",
        "url": "https://www.reed.co.uk/jobs/java-software-engineer/56427863",
        "raw": {
          "jobId": 56427863,
          "employerId": 423247,
          "employerName": "Accenture",
          "employerProfileId": null,
          "employerProfileName": null,
          "jobTitle": "Java Software Engineer",
          "locationName": "London",
          "minimumSalary": null,
          "maximumSalary": null,
          "currency": null,
          "expirationDate": "26/05/2026",
          "date": "04/02/2026",
          "jobDescription": "Role: Software Engineer (Java)&nbsp; Level: Associate Manager and Specialist Location: London, Bristol, Manchester and Birmingham Salary: Competitive salary and package (Depending on level of experience) Please Note: Any offer of employment is subject to satisfactory BPSS and SC security clearance which requires 5 years continuous UK address history (typically including no periods of 30 consecutive days or more spent outside of the UK) and decla... ",
          "applications": 106,
          "jobUrl": "https://www.reed.co.uk/jobs/java-software-engineer/56427863"
        }
      },
      "sponsor": {
        "organisation_name": "Accenture (UK) Limited",
        "town_city": "London",
        "county": "NULL",
        "type_rating": "Worker (A rating)",
        "route": "Global Business Mobility: Senior or Specialist Worker"
      }
    },
    {
      "offer": {
        "source": "reed",
        "external_id": 56001798,
        "title": "Software Engineer - Manchester",
        "company": "Accenture",
        "location": "Manchester",
        "salary_min": null,
        "salary_max": null,
        "currency": "GBP",
        "contract_type": null,
        "contract_time": null,
        "posted_at": "30/10/2025",
        "url": "https://www.reed.co.uk/jobs/software-engineer-manchester/56001798",
        "raw": {
          "jobId": 56001798,
          "employerId": 423247,
          "employerName": "Accenture",
          "employerProfileId": null,
          "employerProfileName": null,
          "jobTitle": "Software Engineer - Manchester",
          "locationName": "Manchester",
          "minimumSalary": null,
          "maximumSalary": null,
          "currency": null,
          "expirationDate": "26/05/2026",
          "date": "30/10/2025",
          "jobDescription": "Role: Software Engineer - Manchester Level: 9 - Specialist Please Note: Any offer of employment is subject to satisfactory SC security clearance which requires 5 years continuous UK address history, typically including no periods of 30 consecutive days or more spent outside of the UK. Note: The above information relates to a specific client requirement &nbsp; Accenture is a leading global professional services company, providing a broad range of... ",
          "applications": 184,
          "jobUrl": "https://www.reed.co.uk/jobs/software-engineer-manchester/56001798"
        }
      },
      "sponsor": {
        "organisation_name": "Accenture (UK) Limited",
        "town_city": "London",
        "county": "NULL",
        "type_rating": "Worker (A rating)",
        "route": "Skilled Worker"
      }
    },
    {
      "offer": {
        "source": "reed",
        "external_id": 56001798,
        "title": "Software Engineer - Manchester",
        "company": "Accenture",
        "location": "Manchester",
        "salary_min": null,
        "salary_max": null,
        "currency": "GBP",
        "contract_type": null,
        "contract_time": null,
        "posted_at": "30/10/2025",
        "url": "https://www.reed.co.uk/jobs/software-engineer-manchester/56001798",
        "raw": {
          "jobId": 56001798,
          "employerId": 423247,
          "employerName": "Accenture",
          "employerProfileId": null,
          "employerProfileName": null,
          "jobTitle": "Software Engineer - Manchester",
          "locationName": "Manchester",
          "minimumSalary": null,
          "maximumSalary": null,
          "currency": null,
          "expirationDate": "26/05/2026",
          "date": "30/10/2025",
          "jobDescription": "Role: Software Engineer - Manchester Level: 9 - Specialist Please Note: Any offer of employment is subject to satisfactory SC security clearance which requires 5 years continuous UK address history, typically including no periods of 30 consecutive days or more spent outside of the UK. Note: The above information relates to a specific client requirement &nbsp; Accenture is a leading global professional services company, providing a broad range of... ",
          "applications": 184,
          "jobUrl": "https://www.reed.co.uk/jobs/software-engineer-manchester/56001798"
        }
      },
      "sponsor": {
        "organisation_name": "Accenture (UK) Limited",
        "town_city": "London",
        "county": "NULL",
        "type_rating": "Worker (A rating)",
        "route": "Global Business Mobility: Senior or Specialist Worker"
      }
    },
    {
      "offer": {
        "source": "reed",
        "external_id": 56782846,
        "title": "Senior Software Developer",
        "company": "Birketts LLP",
        "location": "Sevenoaks",
        "salary_min": null,
        "salary_max": null,
        "currency": "GBP",
        "contract_type": null,
        "contract_time": null,
        "posted_at": "14/04/2026",
        "url": "https://www.reed.co.uk/jobs/senior-software-developer/56782846",
        "raw": {
          "jobId": 56782846,
          "employerId": 497596,
          "employerName": "Birketts LLP",
          "employerProfileId": null,
          "employerProfileName": null,
          "jobTitle": "Senior Software Developer",
          "locationName": "Sevenoaks",
          "minimumSalary": null,
          "maximumSalary": null,
          "currency": null,
          "expirationDate": "26/05/2026",
          "date": "14/04/2026",
          "jobDescription": "About us Birketts is a full service, UK Top 50 law firm. With a heritage spanning 160 years, we have more than 700 lawyers and legal professionals and over 600 staff based in Bristol, Cambridge, Chelmsford, Ipswich, London, Norwich and Sevenoaks. We advise businesses, government and public sector organisations and individuals in the UK and internationally across four principal practice groups: Real Estate, Corporate Services, Dispute Resolution ... ",
          "applications": 3,
          "jobUrl": "https://www.reed.co.uk/jobs/senior-software-developer/56782846"
        }
      },
      "sponsor": {
        "organisation_name": "Birketts LLP",
        "town_city": "Chelmsford",
        "county": "",
        "type_rating": "Worker (A rating)",
        "route": "Skilled Worker"
      }
    },
    {
      "offer": {
        "source": "reed",
        "external_id": 56718574,
        "title": "Software Developer (.NET/AWS)",
        "company": "Verisk",
        "location": "NR11BD",
        "salary_min": 45000.0,
        "salary_max": 50000.0,
        "currency": "GBP",
        "contract_type": null,
        "contract_time": null,
        "posted_at": "31/03/2026",
        "url": "https://www.reed.co.uk/jobs/software-developer-net-aws/56718574",
        "raw": {
          "jobId": 56718574,
          "employerId": 665071,
          "employerName": "Verisk",
          "employerProfileId": null,
          "employerProfileName": null,
          "jobTitle": "Software Developer (.NET/AWS)",
          "locationName": "NR11BD",
          "minimumSalary": 45000.0,
          "maximumSalary": 50000.0,
          "currency": "GBP",
          "expirationDate": "12/05/2026",
          "date": "31/03/2026",
          "jobDescription": "Our platform is evolving towards a modern AWS-native architecture, making extensive use of serverless technologies, microservices and event-driven systems to deliver highly scalable and reliable solutions. You will help design and develop scalable distributed systems and shared services that support multiple products used by insurers, suppliers, police forces and supporting organisations across the UK and internationally. You will work across th... ",
          "applications": 35,
          "jobUrl": "https://www.reed.co.uk/jobs/software-developer-net-aws/56718574"
        }
      },
      "sponsor": {
        "organisation_name": "Verisk Analytics Limited",
        "town_city": "London",
        "county": "NULL",
        "type_rating": "Worker (A rating)",
        "route": "Skilled Worker"
      }
    },
    {
      "offer": {
        "source": "reed",
        "external_id": 56718574,
        "title": "Software Developer (.NET/AWS)",
        "company": "Verisk",
        "location": "NR11BD",
        "salary_min": 45000.0,
        "salary_max": 50000.0,
        "currency": "GBP",
        "contract_type": null,
        "contract_time": null,
        "posted_at": "31/03/2026",
        "url": "https://www.reed.co.uk/jobs/software-developer-net-aws/56718574",
        "raw": {
          "jobId": 56718574,
          "employerId": 665071,
          "employerName": "Verisk",
          "employerProfileId": null,
          "employerProfileName": null,
          "jobTitle": "Software Developer (.NET/AWS)",
          "locationName": "NR11BD",
          "minimumSalary": 45000.0,
          "maximumSalary": 50000.0,
          "currency": "GBP",
          "expirationDate": "12/05/2026",
          "date": "31/03/2026",
          "jobDescription": "Our platform is evolving towards a modern AWS-native architecture, making extensive use of serverless technologies, microservices and event-driven systems to deliver highly scalable and reliable solutions. You will help design and develop scalable distributed systems and shared services that support multiple products used by insurers, suppliers, police forces and supporting organisations across the UK and internationally. You will work across th... ",
          "applications": 35,
          "jobUrl": "https://www.reed.co.uk/jobs/software-developer-net-aws/56718574"
        }
      },
      "sponsor": {
        "organisation_name": "Verisk Analytics Limited",
        "town_city": "London",
        "county": "NULL",
        "type_rating": "Worker (A rating)",
        "route": "Global Business Mobility: Senior or Specialist Worker"
      }
    }
  ]
}