{
  "overview": {
    "total_jobs": 273,
    "matched_jobs": 85,
    "high_confidence_jobs": 52,
    "weighted_matched_jobs": 65.1,
    "weighted_high_confidence_jobs": 52.0,
    "match_rate": 0.2385,
    "high_confidence_rate": 0.1905
  },
  "locations": [
    {
      "location": "London",
      "weighted_count": 24.15,
      "raw_count": 30
    },
    {
      "location": "Bristol",
      "weighted_count": 5.55,
      "raw_count": 7
    },
    {
      "location": "Manchester",
      "weighted_count": 3.2,
      "raw_count": 5
    },
    {
      "location": "Glasgow",
      "weighted_count": 3.2,
      "raw_count": 4
    },
    {
      "location": "Isleworth, West London",
      "weighted_count": 3.0,
      "raw_count": 3
    },
    {
      "location": "Leeds",
      "weighted_count": 2.5,
      "raw_count": 3
    },
    {
      "location": "London, UK",
      "weighted_count": 2.25,
      "raw_count": 4
    },
    {
      "location": "Firswood, Manchester",
      "weighted_count": 2.0,
      "raw_count": 2
    },
    {
      "location": "Ocean Village, Southampton",
      "weighted_count": 2.0,
      "raw_count": 2
    },
    {
      "location": "Altrincham, Greater Manchester",
      "weighted_count": 1.0,
      "raw_count": 1
    },
    {
      "location": "Baguley, Manchester",
      "weighted_count": 1.0,
      "raw_count": 1
    },
    {
      "location": "Boningale, Albrighton",
      "weighted_count": 1.0,
      "raw_count": 1
    },
    {
      "location": "Bristol, South West England",
      "weighted_count": 1.0,
      "raw_count": 1
    },
    {
      "location": "Chew Stoke, Bristol",
      "weighted_count": 1.0,
      "raw_count": 1
    },
    {
      "location": "Clapton In Gordano, Bristol",
      "weighted_count": 1.0,
      "raw_count": 1
    },
    {
      "location": "Glasgow, Scotland",
      "weighted_count": 1.0,
      "raw_count": 1
    },
    {
      "location": "Liverpool",
      "weighted_count": 1.0,
      "raw_count": 1
    },
    {
      "location": "Rusholme, Manchester",
      "weighted_count": 1.0,
      "raw_count": 1
    },
    {
      "location": "Southampton",
      "weighted_count": 1.0,
      "raw_count": 1
    },
    {
      "location": "Southwick, Brighton",
      "weighted_count": 1.0,
      "raw_count": 1
    },
    {
      "location": "Victoria, South West London",
      "weighted_count": 1.0,
      "raw_count": 1
    },
    {
      "location": "Walworth, South East London",
      "weighted_count": 1.0,
      "raw_count": 1
    },
    {
      "location": "Hammersmith, West London",
      "weighted_count": 0.85,
      "raw_count": 1
    },
    {
      "location": "Belfast, Northern Ireland",
      "weighted_count": 0.5,
      "raw_count": 1
    },
    {
      "location": "Enfield, London",
      "weighted_count": 0.5,
      "raw_count": 1
    },
    {
      "location": "Hillhead, Glasgow City Centre",
      "weighted_count": 0.5,
      "raw_count": 1
    },
    {
      "location": "Willesden, North West London",
      "weighted_count": 0.5,
      "raw_count": 1
    },
    {
      "location": "Brighton",
      "weighted_count": 0.4,
      "raw_count": 2
    },
    {
      "location": "Custom House, East London",
      "weighted_count": 0.2,
      "raw_count": 1
    },
    {
      "location": "Kensington, West London",
      "weighted_count": 0.2,
      "raw_count": 1
    },
    {
      "location": "Stockwell, South West London",
      "weighted_count": 0.2,
      "raw_count": 1
    },
    {
      "location": "Streatham, South West London",
      "weighted_count": 0.2,
      "raw_count": 1
    },
    {
      "location": "Walthamstow, East London",
      "weighted_count": 0.2,
      "raw_count": 1
    }
  ],
  "employers": [
    {
      "company": "Southwark Council",
      "weighted_count": 11.0,
      "raw_count": 11
    },
    {
      "company": "Pearson Plc",
      "weighted_count": 8.0,
      "raw_count": 8
    },
    {
      "company": "Uber eats",
      "weighted_count": 5.0,
      "raw_count": 5
    },
    {
      "company": "Sky",
      "weighted_count": 4.0,
      "raw_count": 4
    },
    {
      "company": "Network Plus",
      "weighted_count": 3.0,
      "raw_count": 3
    },
    {
      "company": "Robert Half",
      "weighted_count": 3.0,
      "raw_count": 3
    },
    {
      "company": "MEARS GROUP PLC",
      "weighted_count": 2.0,
      "raw_count": 2
    },
    {
      "company": "Robert Walters",
      "weighted_count": 2.0,
      "raw_count": 2
    },
    {
      "company": "Witherslack Group",
      "weighted_count": 2.0,
      "raw_count": 2
    },
    {
      "company": "Adecco",
      "weighted_count": 1.0,
      "raw_count": 1
    },
    {
      "company": "Aspire People Limited",
      "weighted_count": 1.0,
      "raw_count": 1
    },
    {
      "company": "Aviva",
      "weighted_count": 1.0,
      "raw_count": 1
    },
    {
      "company": "Calor Gas Limited",
      "weighted_count": 1.0,
      "raw_count": 1
    },
    {
      "company": "Handle Recruitment",
      "weighted_count": 1.0,
      "raw_count": 1
    },
    {
      "company": "Mr Clutch Autocentres",
      "weighted_count": 1.0,
      "raw_count": 1
    },
    {
      "company": "NEWTO TRAINING LIMITED",
      "weighted_count": 1.0,
      "raw_count": 1
    },
    {
      "company": "NonStop Consulting Ltd",
      "weighted_count": 1.0,
      "raw_count": 1
    },
    {
      "company": "Public House Group Limited",
      "weighted_count": 1.0,
      "raw_count": 1
    },
    {
      "company": "Sphere Digital Recruitment",
      "weighted_count": 1.0,
      "raw_count": 1
    },
    {
      "company": "Teleperformance",
      "weighted_count": 1.0,
      "raw_count": 1
    },
    {
      "company": "eFinancialCareers",
      "weighted_count": 1.0,
      "raw_count": 1
    }
  ],
  "titles": [
    {
      "title": "Other",
      "weighted_count": 22.65,
      "raw_count": 26
    },
    {
      "title": "Operations / Project Management",
      "weighted_count": 8.5,
      "raw_count": 12
    },
    {
      "title": "Data / AI",
      "weighted_count": 6.6,
      "raw_count": 10
    },
    {
      "title": "Administration / Office",
      "weighted_count": 4.5,
      "raw_count": 6
    },
    {
      "title": "Nursing / Care",
      "weighted_count": 3.4,
      "raw_count": 5
    },
    {
      "title": "Creative / Media",
      "weighted_count": 3.0,
      "raw_count": 3
    },
    {
      "title": "Education / Teaching",
      "weighted_count": 3.0,
      "raw_count": 3
    },
    {
      "title": "Finance / Accounting",
      "weighted_count": 2.2,
      "raw_count": 5
    },
    {
      "title": "Skilled Trades",
      "weighted_count": 2.0,
      "raw_count": 3
    },
    {
      "title": "Real Estate / Property",
      "weighted_count": 2.0,
      "raw_count": 2
    },
    {
      "title": "Cybersecurity / InfoSec",
      "weighted_count": 1.5,
      "raw_count": 2
    },
    {
      "title": "Consulting",
      "weighted_count": 1.0,
      "raw_count": 1
    },
    {
      "title": "DevOps / Cloud",
      "weighted_count": 1.0,
      "raw_count": 1
    },
    {
      "title": "Electrical Engineering",
      "weighted_count": 1.0,
      "raw_count": 1
    },
    {
      "title": "Insurance",
      "weighted_count": 1.0,
      "raw_count": 1
    },
    {
      "title": "Construction",
      "weighted_count": 0.85,
      "raw_count": 1
    },
    {
      "title": "Banking / Financial Services",
      "weighted_count": 0.5,
      "raw_count": 1
    },
    {
      "title": "Hospitality",
      "weighted_count": 0.4,
      "raw_count": 2
    }
  ],
  "routes": [
    {
      "route": "Skilled Worker",
      "weighted_count": 39.1,
      "raw_count": 57
    },
    {
      "route": "Global Business Mobility: Senior or Specialist Worker",
      "weighted_count": 20.5,
      "raw_count": 21
    },
    {
      "route": "Creative Worker",
      "weighted_count": 5.5,
      "raw_count": 7
    }
  ],
  "seniority": [
    {
      "level": "Standard",
      "weighted_count": 47.35,
      "raw_count": 58
    },
    {
      "level": "Leadership",
      "weighted_count": 12.35,
      "raw_count": 20
    },
    {
      "level": "Senior",
      "weighted_count": 3.4,
      "raw_count": 5
    },
    {
      "level": "Entry",
      "weighted_count": 2.0,
      "raw_count": 2
    }
  ],
  "scores": [
    {
      "label": "1.00 exact_normalized",
      "weighted_count": 52.0,
      "raw_count": 52
    },
    {
      "label": "0.50 recruiter_or_ambiguous",
      "weighted_count": 6.5,
      "raw_count": 13
    },
    {
      "label": "0.85 fuzzy_strong",
      "weighted_count": 3.4,
      "raw_count": 4
    },
    {
      "label": "0.20 substring_only",
      "weighted_count": 3.2,
      "raw_count": 16
    },
    {
      "label": "0.92 alias_table",
      "weighted_count": 0.0,
      "raw_count": 0
    }
  ]
}